zeroband/__init__.py
zeroband/language_models/__init__.py
zeroband/language_models/anthropic.py
zeroband/language_models/base_language_model.py
zeroband/language_models/gemini.py
zeroband/language_models/openai.py
zeroband/main.py
zeroband/strategies/__init__.py
zeroband/strategies/base_strategy.py
zeroband/strategies/cot.py
zeroband/strategies/pot.py
zeroband/strategies/tir.py
zeroband/tools/__init__.py
zeroband/tools/base_tool.py
zeroband/tools/calculator.py
zeroband/tools/linux_term.py
zeroband/tools/sql_db.py
zeroband/tools/symbolic_solver.py
zeroband/tools/web_search.py
zeroband-0.0.2.dist-info/LICENSE
zeroband-0.0.2.dist-info/METADATA
zeroband-0.0.2.dist-info/WHEEL
zeroband-0.0.2.dist-info/RECORD
