Metadata-Version: 2.1
Name: zeroband
Version: 0.0.2
Summary: stealth stealth very sneaky
Author: Jackmin801
Author-email: ongjackm@gmail.com
Requires-Python: >=3.11,<4.0
Classifier: Programming Language :: Python :: 3
Classifier: Programming Language :: Python :: 3.11
Classifier: Programming Language :: Python :: 3.12
Requires-Dist: datasets (>=2.21.0,<3.0.0)
